envtyped/__init__.py
envtyped/config.py
envtyped/helpers.py
envtyped/py.typed
envtyped/repository.py
envtyped-0.1.1.dist-info/LICENSE
envtyped-0.1.1.dist-info/METADATA
envtyped-0.1.1.dist-info/WHEEL
envtyped-0.1.1.dist-info/RECORD
