Metadata-Version: 2.1
Name: envtyped
Version: 0.1.1
Summary: Strong typing for your environment variables
Author: cuire
Author-email: 81014305+cuire@users.noreply.github.com
Requires-Python: >=3.10,<4.0
Classifier: Programming Language :: Python :: 3
Classifier: Programming Language :: Python :: 3.10
Classifier: Programming Language :: Python :: 3.11
Classifier: Programming Language :: Python :: 3.12
